{
  "table_id": "T3127",
  "uid": "2430c22b-67a7-5127-a1d7-f089141a7b61",
  "source": "HybridQA",
  "source_table_id": "2430c22b-67a7-5127-a1d7-f089141a7b61",
  "domain": "HybridQA",
  "title": "Heartland Championship",
  "columns": [
    "Team",
    "Titles",
    "Runners-up",
    "Years"
  ],
  "rows": [
    [
      [
        "Wanganui",
        [
          "/wiki/Wanganui_Rugby_Football_Union"
        ]
      ],
      [
        6,
        []
      ],
      [
        4,
        []
      ],
      [
        "2008 , 2009 , 2011 , 2015 , 2016 , 2017",
        [
          "/wiki/2008_Heartland_Championship",
          "/wiki/2009_Heartland_Championship",
          "/wiki/2011_Heartland_Championship",
          "/wiki/2015_Heartland_Championship",
          "/wiki/2016_Heartland_Championship"
        ]
      ]
    ],
    [
      [
        "Mid Canterbury",
        [
          "/wiki/Mid_Canterbury_Rugby_Football_Union"
        ]
      ],
      [
        2,
        []
      ],
      [
        2,
        []
      ],
      [
        "2013 , 2014",
        [
          "/wiki/2013_Heartland_Championship",
          "/wiki/2014_Heartland_Championship"
        ]
      ]
    ],
    [
      [
        "North Otago",
        [
          "/wiki/North_Otago_Rugby_Football_Union"
        ]
      ],
      [
        2,
        []
      ],
      [
        1,
        []
      ],
      [
        "2007 , 2010",
        [
          "/wiki/2007_Heartland_Championship",
          "/wiki/2010_Heartland_Championship"
        ]
      ]
    ],
    [
      [
        "East Coast",
        [
          "/wiki/East_Coast_Rugby_Football_Union"
        ]
      ],
      [
        1,
        []
      ],
      [
        1,
        []
      ],
      [
        2012,
        [
          "/wiki/2012_Heartland_Championship"
        ]
      ]
    ],
    [
      [
        "Thames Valley",
        [
          "/wiki/Thames_Valley_Rugby_Football_Union"
        ]
      ],
      [
        1,
        []
      ],
      [
        0,
        []
      ],
      [
        2018,
        []
      ]
    ],
    [
      [
        "Wairarapa Bush",
        [
          "/wiki/Wairarapa_Bush_Rugby_Football_Union"
        ]
      ],
      [
        1,
        []
      ],
      [
        1,
        []
      ],
      [
        2006,
        [
          "/wiki/2006_Heartland_Championship"
        ]
      ]
    ],
    [
      [
        "Buller",
        [
          "/wiki/Buller_Rugby_Football_Union"
        ]
      ],
      [
        0,
        []
      ],
      [
        2,
        []
      ],
      [
        0,
        []
      ]
    ],
    [
      [
        "South Canterbury",
        [
          "/wiki/South_Canterbury_Rugby_Football_Union"
        ]
      ],
      [
        0,
        []
      ],
      [
        2,
        []
      ],
      [
        0,
        []
      ]
    ],
    [
      [
        "Horowhenua-Kapiti",
        [
          "/wiki/Horowhenua-Kapiti_Rugby_Football_Union"
        ]
      ],
      [
        0,
        []
      ],
      [
        1,
        []
      ],
      [
        0,
        []
      ]
    ]
  ],
  "corpus_table": {
    "uid": "2430c22b-67a7-5127-a1d7-f089141a7b61",
    "table_id": "Heartland_Championship_1",
    "title": "Heartland Championship",
    "header": [
      "Team",
      "Titles",
      "Runners-up",
      "Years"
    ],
    "value": [
      [
        [
          "Wanganui",
          [
            "/wiki/Wanganui_Rugby_Football_Union"
          ]
        ],
        [
          6,
          []
        ],
        [
          4,
          []
        ],
        [
          "2008 , 2009 , 2011 , 2015 , 2016 , 2017",
          [
            "/wiki/2008_Heartland_Championship",
            "/wiki/2009_Heartland_Championship",
            "/wiki/2011_Heartland_Championship",
            "/wiki/2015_Heartland_Championship",
            "/wiki/2016_Heartland_Championship"
          ]
        ]
      ],
      [
        [
          "Mid Canterbury",
          [
            "/wiki/Mid_Canterbury_Rugby_Football_Union"
          ]
        ],
        [
          2,
          []
        ],
        [
          2,
          []
        ],
        [
          "2013 , 2014",
          [
            "/wiki/2013_Heartland_Championship",
            "/wiki/2014_Heartland_Championship"
          ]
        ]
      ],
      [
        [
          "North Otago",
          [
            "/wiki/North_Otago_Rugby_Football_Union"
          ]
        ],
        [
          2,
          []
        ],
        [
          1,
          []
        ],
        [
          "2007 , 2010",
          [
            "/wiki/2007_Heartland_Championship",
            "/wiki/2010_Heartland_Championship"
          ]
        ]
      ],
      [
        [
          "East Coast",
          [
            "/wiki/East_Coast_Rugby_Football_Union"
          ]
        ],
        [
          1,
          []
        ],
        [
          1,
          []
        ],
        [
          2012,
          [
            "/wiki/2012_Heartland_Championship"
          ]
        ]
      ],
      [
        [
          "Thames Valley",
          [
            "/wiki/Thames_Valley_Rugby_Football_Union"
          ]
        ],
        [
          1,
          []
        ],
        [
          0,
          []
        ],
        [
          2018,
          []
        ]
      ],
      [
        [
          "Wairarapa Bush",
          [
            "/wiki/Wairarapa_Bush_Rugby_Football_Union"
          ]
        ],
        [
          1,
          []
        ],
        [
          1,
          []
        ],
        [
          2006,
          [
            "/wiki/2006_Heartland_Championship"
          ]
        ]
      ],
      [
        [
          "Buller",
          [
            "/wiki/Buller_Rugby_Football_Union"
          ]
        ],
        [
          0,
          []
        ],
        [
          2,
          []
        ],
        [
          0,
          []
        ]
      ],
      [
        [
          "South Canterbury",
          [
            "/wiki/South_Canterbury_Rugby_Football_Union"
          ]
        ],
        [
          0,
          []
        ],
        [
          2,
          []
        ],
        [
          0,
          []
        ]
      ],
      [
        [
          "Horowhenua-Kapiti",
          [
            "/wiki/Horowhenua-Kapiti_Rugby_Football_Union"
          ]
        ],
        [
          0,
          []
        ],
        [
          1,
          []
        ],
        [
          0,
          []
        ]
      ]
    ]
  },
  "description": "The table provides an overview of teams participating in the Heartland Championship, a rugby competition, along with their achievements. It includes information on the number of titles won, instances of being runners-up, and the years associated with these accomplishments. The table serves to summarize team performance and historical data in the championship.",
  "numeric_columns": [
    "Titles",
    "Runners-up"
  ],
  "categorical_columns": [
    "Years"
  ],
  "entities": [
    "Team"
  ]
}